fluentcheck/__init__.py
fluentcheck/exceptions.py
fluentcheck/assertions_check/__init__.py
fluentcheck/assertions_check/booleans.py
fluentcheck/assertions_check/collections.py
fluentcheck/assertions_check/dicts.py
fluentcheck/assertions_check/geo.py
fluentcheck/assertions_check/numbers.py
fluentcheck/assertions_check/sequences.py
fluentcheck/assertions_check/strings.py
fluentcheck/assertions_check/types.py
fluentcheck/assertions_check/uuids.py
fluentcheck/assertions_is/__init__.py
fluentcheck/assertions_is/base_is.py
fluentcheck/assertions_is/booleans.py
fluentcheck/assertions_is/collections.py
fluentcheck/assertions_is/dicts.py
fluentcheck/assertions_is/emptiness.py
fluentcheck/assertions_is/geo.py
fluentcheck/assertions_is/numbers.py
fluentcheck/assertions_is/sequences.py
fluentcheck/assertions_is/strings.py
fluentcheck/assertions_is/types.py
fluentcheck/assertions_is/uuids.py
fluentcheck/classes/__init__.py
fluentcheck/classes/check.py
fluentcheck/classes/is_cls.py
fluentcheck/tests/__init__.py
fluentcheck/tests/tests_check/__init__.py
fluentcheck/tests/tests_check/test_basic_checks.py
fluentcheck/tests/tests_check/test_booleans.py
fluentcheck/tests/tests_check/test_collections.py
fluentcheck/tests/tests_check/test_dicts.py
fluentcheck/tests/tests_check/test_numbers.py
fluentcheck/tests/tests_check/test_strings.py
fluentcheck/tests/tests_check/test_type_hierarchy.py
fluentcheck/tests/tests_check/test_uuids.py
fluentcheck/tests/tests_is/__init__.py
fluentcheck/tests/tests_is/test_basic_checks_is.py
fluentcheck/tests/tests_is/test_booleans_is.py
fluentcheck/tests/tests_is/test_chain_closure_is.py
fluentcheck/tests/tests_is/test_collections_is.py
fluentcheck/tests/tests_is/test_dicts_is.py
fluentcheck/tests/tests_is/test_numbers_is.py
fluentcheck/tests/tests_is/test_sequences_is.py
fluentcheck/tests/tests_is/test_strings_is.py
fluentcheck/tests/tests_is/test_type_hierarchy_is.py
fluentcheck-0.2.0.dist-info/DESCRIPTION.rst
fluentcheck-0.2.0.dist-info/METADATA
fluentcheck-0.2.0.dist-info/RECORD
fluentcheck-0.2.0.dist-info/WHEEL
fluentcheck-0.2.0.dist-info/metadata.json
fluentcheck-0.2.0.dist-info/top_level.txt
